Topsis/__init__.py
Topsis/__main__.py
Topsis_Jasmeet_102116124-0.0.0.dist-info/LICENSE
Topsis_Jasmeet_102116124-0.0.0.dist-info/METADATA
Topsis_Jasmeet_102116124-0.0.0.dist-info/WHEEL
Topsis_Jasmeet_102116124-0.0.0.dist-info/entry_points.txt
Topsis_Jasmeet_102116124-0.0.0.dist-info/top_level.txt
Topsis_Jasmeet_102116124-0.0.0.dist-info/RECORD
