Metadata-Version: 2.1
Name: Topsis-Jasmeet-102116124
Version: 0.0.0
Summary: TOPSIS implementation by Jasmeet Kaur
Home-page: https://github.com/Jasmeet-Kaur16/Topsis-Jasmeet-102116124
Author: Jasmeet Kaur
Author-email: jasmeet.k.2003@gmail.com
License: MIT
Classifier: License :: OSI Approved :: MIT License
Classifier: Programming Language :: Python :: 3.6
Classifier: Programming Language :: Python :: 3.7
Classifier: Programming Language :: Python :: 3.8
License-File: LICENSE
Requires-Dist: numpy
Requires-Dist: pandas
Requires-Dist: sys
